[{"section_title": "Epidemiology Communicable diseases", "text": "Epidemiologic surveillance"}, {"section_title": "Introducci\u00f3n", "text": "La enfermedad por coronavirus (COVID-19) se comunic\u00f3 por primera vez en China en diciembre de 2019 y en poco m\u00e1s de 3 meses se ha extendido a m\u00e1s de cien pa\u00edses 1 .\nEs una enfermedad sin tratamiento farmacol\u00f3gico espec\u00edfico y con unos mecanismos de transmisibilidad y letalidad poco conocidos. Estas caracter\u00edsticas dificultan la implantaci\u00f3n de intervenciones sanitarias por parte de los sistemas de salud. A este escenario se agregan la diversidad de aspectos econ\u00f3micos, sociales y demogr\u00e1ficos, y las capacidades de los sistemas de salud para identificar y ofrecer atenci\u00f3n m\u00e9dica a las personas afectadas.\nLa evoluci\u00f3n de esta pandemia, en t\u00e9rminos de incidencia, mortalidad y velocidad de expansi\u00f3n, es heterog\u00e9nea, con diferencias entre pa\u00edses e incluso entre regiones del mismo pa\u00eds. Esto requiere comprender los elementos que impulsan su comportamiento 1 .\nAlgunos estudios muestran que existen diferencias en la presentaci\u00f3n cl\u00ednica y en la gravedad de la enfermedad, y que la letalidad es mayor en las personas mayores 2 .\nAdem\u00e1s, una parte de los infectados requerir\u00e1 asistencia sanitaria, incluyendo hospitalizaci\u00f3n 3 . Por lo tanto, la estructura y la capacidad de los sistemas sanitarios son importantes para el impacto de la epidemia.\nEste estudio tiene por objetivo analizar factores asociados al impacto de la epidemia de COVID-19 en pa\u00edses de diversos continentes a partir de indicadores de morbilidad y mortalidad. Para ello, se describe y analiza la asociaci\u00f3n de una selecci\u00f3n de indicadores relacionados con la capacidad asistencial de los sistemas de salud y las caracter\u00edsticas demogr\u00e1ficas de los pa\u00edses seleccionados, as\u00ed como los elementos que caracterizan el proceso epid\u00e9mico, como la magnitud, la velocidad de propagaci\u00f3n y la letalidad."}, {"section_title": "M\u00e9todo", "text": "Estudio ecol\u00f3gico basado en datos secundarios de China y de los pa\u00edses de la Organizaci\u00f3n para la Cooperaci\u00f3n y el Desarrollo Econ\u00f3mico (OCDE) con m\u00e1s de 200 casos notificados hasta el 18 de marzo de 2020 4 . Estos pa\u00edses concentran la gran mayor\u00eda de los casos y tienen caracter\u00edsticas socioecon\u00f3micas relativamente homog\u00e9neas.\nPage 4 of 9 J o u r n a l P r e -p r o o f 4 Se han seleccionado los indicadores del Banco Mundial de \u00abdensidad de poblaci\u00f3n\u00bb y \u00abporcentaje de personas mayores de 65 a\u00f1os\u00bb de cada pa\u00eds, debido a que pueden ser factores importantes en la propagaci\u00f3n de la epidemia y en su impacto en la mortalidad 5, 6 . Se han incluido los indicadores de la OCDE sobre \u00abgasto per c\u00e1pita en salud\u00bb, \u00abgasto en salud como porcentaje del producto interior bruto\u00bb, \u00abn\u00famero de profesionales de medicina\u00bb y \u00abn\u00famero de camas de hospital por habitante\u00bb, los cuales muestran la capacidad de cada pa\u00eds para responder a la epidemia 7 . Se han incluido tambi\u00e9n las estimaciones del n\u00famero de pruebas de COVID-19 por mill\u00f3n de personas realizadas en los pa\u00edses del estudio, publicadas en el blog Our World in Data, basadas en fuentes oficiales, para identificar la capacidad diagn\u00f3stica de los respectivos sistema sanitarios 8 .\nEl n\u00famero de casos y el n\u00famero de muertes confirmadas se han obtenido del Centro Europeo para la Prevenci\u00f3n y el Control de Enfermedades 4 . Con estos datos se han estimado las variables respuesta para identificar el impacto de la epidemia, las tasas de incidencia y de mortalidad, y la letalidad. Las tasas de incidencia y la mortalidad se han calculado a partir del n\u00famero de casos confirmados y del n\u00famero de muertes por COVID-19, y para los denominadores se han utilizado las poblaciones de los pa\u00edses, disponibles en el repositorio de la Organizaci\u00f3n Mundial de Salud 9 . La letalidad se ha calculado como el n\u00famero de muertes en funci\u00f3n del n\u00famero de casos confirmados de COVID-19. Adem\u00e1s, se han incluido como variables explicativas del proceso epid\u00e9mico el tiempo desde el primer caso y el tiempo para llegar a los 100 casos, que se han calculado con los datos de las fechas de los casos y de las muertes.\nPara identificar diferencias en la letalidad se ha desarrollado un \u00edndice de letalidad relativa, utilizando la tasa de letalidad del brote de COVID-19 en el crucero Princess Diamond como referencia 10 . Este \u00edndice es la letalidad de cada pa\u00eds en relaci\u00f3n con la letalidad que hubo en el crucero. En este, se realiz\u00f3 seguimiento a una gran mayor\u00eda de pasaje y tripulaci\u00f3n, 3710 personas en total, lo que ha permitido calcular la letalidad con una precisi\u00f3n muy superior a la que se puede estimar actualmente en los pa\u00edses afectados. Adem\u00e1s, la mayor\u00eda de los casos se detectaron en pacientes nacidos en pa\u00edses de la OCDE 10 , similares a los incluidos en este estudio. Hubo siete muertes, todas en pacientes mayores de 70 a\u00f1os, resultando una tasa de letalidad del 1,01% 10 .\nSe ha utilizado el coeficiente de correlaci\u00f3n de Spearman para estimar la magnitud de la asociaci\u00f3n entre las variables."}, {"section_title": "Resultados", "text": "Hay una gran heterogeneidad entre los pa\u00edses en cuanto a los indicadores incluidos en el estudio (Tabla I del Ap\u00e9ndice online). La tasa de incidencia no se asocia con el tiempo transcurrido desde el primer caso registrado (p = 0,32) y presenta una correlaci\u00f3n moderada positiva con la tasa de pruebas realizadas para COVID-19 (p <0,05) y con el n\u00famero de profesionales de medicina por habitante en el pa\u00eds (p <0,05). El pa\u00eds con mayor incidencia es Islandia, que pertenece al grupo de pa\u00edses europeos que han comenzado a registrar y comunicar los casos m\u00e1s recientemente. En cuanto a la velocidad de progresi\u00f3n, hay una correlaci\u00f3n moderada negativa entre la incidencia y el tiempo para llegar a los 100 casos, que se\u00f1ala que el grupo de pa\u00edses que ha comenzado a registrar casos m\u00e1s tarde ha tenido menos tiempo desde el inicio de la epidemia para llegar a los 100 casos (p <0,05). Por otra parte, hay una correlaci\u00f3n moderada positiva entre la tasa de incidencia y la tasa de mortalidad (p <0,05), y la tasa de mortalidad est\u00e1 asociada de forma positiva y fuertemente con la letalidad (p <0,01).\nSin embargo, no hay asociaci\u00f3n entre la proporci\u00f3n de personas mayores de 65 a\u00f1os y la tasa de mortalidad ni la letalidad. Tampoco las variables relacionadas con la estructura f\u00edsica y el gasto de los sistemas de salud se asocian con la letalidad y la mortalidad. La letalidad se asocia con el momento de inicio de la epidemia (p <0,05).\nFinalmente, Italia tiene la mayor letalidad relativa, una letalidad 7,9 veces mayor que la estimada para el crucero."}, {"section_title": "Discusi\u00f3n", "text": "La comparaci\u00f3n de los pa\u00edses incluidos en este estudio no presenta los patrones esperados correspondientes a la evoluci\u00f3n de una epidemia de una enfermedad infecciosa con transmisibilidad r\u00e1pida y alta letalidad en personas mayores.\nLa incidencia es una medida de frecuencia que depende de las caracter\u00edsticas relacionadas con el virus, la susceptibilidad a la infecci\u00f3n por parte de la poblaci\u00f3n y la capacidad de los sistemas de salud para identificar a los portadores del virus. La correlaci\u00f3n entre el n\u00famero de pruebas por mill\u00f3n de personas y la incidencia indica que la epidemia puede estar subestimada por la dificultad para hacer el diagn\u00f3stico en algunos pa\u00edses. La falta de correlaci\u00f3n entre la letalidad y la proporci\u00f3n de personas mayores de 65 a\u00f1os es un resultado inesperado, incluso teniendo en cuenta las limitaciones relacionadas con el tipo de dise\u00f1o del estudio, el n\u00famero de pa\u00edses estudiados y el tiempo relativamente corto desde el inicio de la epidemia. Los pa\u00edses que tienen una mayor proporci\u00f3n de personas mayores y un tiempo de epidemia similar deber\u00edan presentar una tasa de letalidad similar. Sin embargo, pa\u00edses como Espa\u00f1a y Alemania presentan una magnitud de la letalidad muy diferente, teniendo una proporci\u00f3n en doi:10.1016\u2026."}, {"section_title": "Editor responsable del art\u00edculo", "text": "Carlos \u00c1lvarez Dardet. \u00bfQu\u00e9 se sabe sobre el tema?\nLa pandemia de COVID-19 se ha extendido r\u00e1pidamente y es un desaf\u00edo para los sistemas sanitarios del mundo. Hay un esfuerzo cient\u00edfico mundial para conocer las caracter\u00edsticas de esta epidemia y permitir el desarrollo de estrategias eficaces de salud p\u00fablica. Sin embargo, poco se sabe sobre los factores que determinan el comportamiento y la evoluci\u00f3n de la epidemia, y los que pueden reducir su impacto sanitario."}, {"section_title": "\u00bfQu\u00e9 a\u00f1ade el estudio realizado a la literatura?", "text": "Las altas tasas de letalidad pueden indicar una transmisi\u00f3n no detectada y una subestimaci\u00f3n de la epidemia. Esta subestimaci\u00f3n debe considerarse para corregir las estimaciones de la incidencia. Se subraya la importancia de mejorar la eficacia de los sistemas de vigilancia epidemiol\u00f3gica, aumentando sus capacidades de detecci\u00f3n de casos y de an\u00e1lisis de datos. Asimismo, la alta letalidad en Espa\u00f1a sugiere una subestimaci\u00f3n de la incidencia y apunta a la necesidad de reforzar la vigilancia epidemiol\u00f3gica y la detecci\u00f3n de casos."}, {"section_title": "Declaraci\u00f3n de transparencia", "text": "El autor principal (garante responsable del manuscrito) afirma que este manuscrito es un reporte honesto, preciso y transparente del estudio que se remite a GACETA SANITARIA, que no se han omitido aspectos importantes del estudio, y que las discrepancias del estudio seg\u00fan lo previsto (y, si son relevantes, registradas) se han explicado."}, {"section_title": "Contribuciones de autor\u00eda", "text": "A. Medeiros de Figueiredo y A. Daponte Codina realizaron la concepci\u00f3n y el dise\u00f1o del estudio, la recogida de los datos y el an\u00e1lisis de los datos. Todos/as los/las autores/as contribuyeron sustancialmente en la interpretaci\u00f3n de los datos y la revisi\u00f3n cr\u00edtica del art\u00edculo. La versi\u00f3n final del art\u00edculo ha sido aprobada para su publicaci\u00f3n por todas las personas firmantes."}]